Workbook

Sheet KAS BESAR PROYEK
A1: KAS BESAR BSI PROYEK | J1: PROYEKSI KAS BESAR BSI 2026
A3: NO. | B3: KET PROYEK | C3: CASH FLOW | I3: PROGRES (%) | J3: KONTRAK DILUAR PP | L3: PENGELUARAN | Q3: MARGIN
C4: DEBIT | D4: KREDIT | E4: Kontrol | F4: TERMIN | G4: SISA TERMIN | L4: TOTAL | M4: VENDOR | N4: ADD VENDOR | O4: FEE | P4: OPERASIONAL + GAJI PENGAWAS
A5: A | B5: PROYEK
A6: 1 | B6: FORD | C6: =ford!D22 -> 20000000 | D6: =ford!F22 -> 18750000 | E6: =C6-D6 -> 1250000 | F6: =ford!D22 -> 20000000 | G6: =J6-F6 -> 0 | I6: =(1- G6/J6) -> 1 | J6: =ford!D9 -> 20000000 | L6: =SUM(M6:P6) -> 18750000 | M6: =ford!E9 -> 17500000 | O6: =ford!F9 -> 1250000 | Q6: =J6-L6 -> 1250000
A7: =A6+1 -> 2 | B7: DESAIN SENDI RSAL | C7: ='D. SENDI RSAL'!D22 -> 4551200 | D7: ='D. SENDI RSAL'!F22 -> 0 | E7: =C7-D7 -> 4551200 | F7: ='D. SENDI RSAL'!D22 -> 4551200 | G7: =J7-F7 -> 0 | I7: 1 | J7: ='D. SENDI RSAL'!D9 -> 4551200 | L7: =SUM(M7:P7) -> 0 | Q7: =J7-L7 -> 4551200
A8: =A7+1 -> 3 | B8: GUDANG JENNY | C8: ='GUDANG JENNY'!D25 -> 53477875 | D8: ='GUDANG JENNY'!F25 -> 66465000 | E8: =C8-D8 -> -12987125 | F8: ='GUDANG JENNY'!D25 -> 53477875 | G8: =J8-F8 -> 53477875 | I8: 1 | J8: ='GUDANG JENNY'!D9 -> 106955750 | L8: =SUM(M8:P8) -> 66465000 | M8: ='GUDANG JENNY'!E9 -> 66265000 | P8: ='GUDANG JENNY'!F23 -> 200000 | Q8: =J8-L8 -> 40490750
A9: =A8+1 -> 4 | B9: CANOPY DEWI | C9: ='CANOPY DEWI'!D22 -> 9000000 | D9: ='CANOPY DEWI'!F22 -> 7500000 | E9: =C9-D9 -> 1500000 | F9: ='CANOPY DEWI'!D22 -> 9000000 | G9: =J9-F9 -> 0 | I9: 1 | J9: ='CANOPY DEWI'!D9 -> 9000000 | L9: =SUM(M9:P9) -> 7500000 | M9: ='CANOPY DEWI'!E9 -> 7500000 | Q9: =J9-L9 -> 1500000
A10: =A9+1 -> 5 | B10: JENDELA KORIDOR DEWI | C10: ='JENDELA KORIDOR DEWI'!D22 -> 8000000 | D10: ='JENDELA KORIDOR DEWI'!F22 -> 5330000 | E10: =C10-D10 -> 2670000 | F10: ='JENDELA KORIDOR DEWI'!D22 -> 8000000 | G10: =J10-F10 -> 0 | I10: 1 | J10: ='JENDELA KORIDOR DEWI'!D9 -> 8000000 | L10: =SUM(M10:P10) -> 5330000 | M10: ='JENDELA KORIDOR DEWI'!E9 -> 5330000 | Q10: =J10-L10 -> 2670000
A11: 6 | B11: NUR EFENDI | C11: ='NUR EFENDI'!D23 -> 73287000 | D11: ='NUR EFENDI'!F23 -> 58218000 | E11: =C11-D11 -> 15069000 | F11: ='NUR EFENDI'!D23 -> 73287000 | G11: =J11-F11 -> 0 | I11: 1 | J11: ='NUR EFENDI'!D9 -> 73287000 | L11: =SUM(M11:P11) -> 58218000 | M11: ='NUR EFENDI'!E9 -> 58000000 | P11: ='NUR EFENDI'!F21 -> 218000 | Q11: =J11-L11 -> 15069000
A12: 7 | B12: DESAIN DEWI K24 | C12: ='D. DEWI K24'!D22 -> 6407500 | D12: ='D. DEWI K24'!F22 -> 9500 | E12: =C12-D12 -> 6398000 | F12: ='D. DEWI K24'!D22 -> 6407500 | G12: =J12-F12 -> 0 | I12: 1 | J12: ='D. DEWI K24'!D9 -> 6407500 | L12: =SUM(M12:P12) -> 9500 | M12: ='D. DEWI K24'!E9 -> 0 | P12: ='D. DEWI K24'!F20 -> 9500 | Q12: =J12-L12 -> 6398000
A13: 8 | B13: DESAIN TENNY BEKASI | C13: ='D. TENNY BEKASI'!D22 -> 600000 | D13: ='D. TENNY BEKASI'!F22 -> 0 | E13: =C13-D13 -> 600000 | F13: ='D. TENNY BEKASI'!D22 -> 600000 | G13: =J13-F13 -> 600000 | I13: 0.9 | J13: ='D. TENNY BEKASI'!D9 -> 1200000 | L13: =SUM(M13:P13) -> 0 | M13: ='D. TENNY BEKASI'!E9 -> 0 | P13: ='D. TENNY BEKASI'!F20 -> 0 | Q13: =J13-L13 -> 1200000
A14: 9 | B14: DESAIN IBU DESY | C14: ='D. DESY'!D22 -> 920000 | D14: ='D. DESY'!F22 -> 0 | E14: =C14-D14 -> 920000 | F14: ='D. DESY'!D22 -> 920000 | G14: =J14-F14 -> 920000 | I14: 0.9 | J14: ='D. DESY'!D9 -> 1840000 | L14: =SUM(M14:P14) -> 0 | M14: ='D. DESY'!E9 -> 0 | P14: ='D. DESY'!F20 -> 0 | Q14: =J14-L14 -> 1840000
A15: 10 | B15: DESAIN IBU ERLIS | C15: ='D. ERLIS'!D22 -> 3570000 | D15: ='D. ERLIS'!F22 -> 50000 | E15: =C15-D15 -> 3520000 | F15: ='D. ERLIS'!D22 -> 3570000 | G15: =J15-F15 -> 3570000 | I15: 0.9 | J15: ='D. ERLIS'!D9 -> 7140000 | L15: =SUM(M15:P15) -> 4145000 | M15: ='D. ERLIS'!E9 -> 4095000 | P15: ='D. ERLIS'!F20 -> 50000 | Q15: =J15-L15 -> 2995000
A16: 11 | B16: BALAI PU | C16: ='balai PU'!D76 -> 1098171914 | D16: ='balai PU'!F76 -> 1018147288 | E16: =C16-D16 -> 80024626 | F16: ='balai PU'!D76 -> 1098171914 | G16: =J16-F16 -> 6.9500043e+08 | I16: 0.75 | J16: ='balai PU'!D13-'balai PU'!E13-'balai PU'!F13 -> 1.7931723e+09 | L16: =SUM(M16:P16) -> 1.440363e+09 | M16: ='balai PU'!G13 -> 1141486268 | N16: ='balai PU'!H13 -> 58237000 | O16: ='balai PU'!I13+'balai PU'!J13 -> 2.2331416e+08 | P16: ='balai PU'!F74+'balai PU'!F23+'balai PU'!F27+'balai PU'!F36+'balai PU'!F49 -> 17325600 | Q16: =J16-L16 -> 3.5280932e+08
A17: 12 | B17: DESAIN HAMSJAH | C17: ='D. HAMSJAH'!D22 -> 4200000 | D17: ='D. HAMSJAH'!F22 -> 0 | E17: =C17-D17 -> 4200000 | F17: ='D. HAMSJAH'!D22 -> 4200000 | G17: =J17-F17 -> 4200000 | I17: 0.75 | J17: ='D. HAMSJAH'!D9 -> 8400000 | L17: =SUM(M17:P17) -> 5325000 | M17: ='D. HAMSJAH'!E5 -> 5325000 | P17: ='D. HAMSJAH'!F20 -> 0 | Q17: =J17-L17 -> 3075000
A18: 13 | B18: DESAIN NANANG | C18: ='D. NANANG'!D22 -> 4750000 | D18: ='D. NANANG'!F22 -> 4900000 | E18: =C18-D18 -> -150000 | F18: ='D. NANANG'!D22 -> 4750000 | G18: =J18-F18 -> 4750000 | I18: 0.5 | J18: ='D. NANANG'!D9 -> 9500000 | L18: =SUM(M18:P18) -> 4900000 | M18: ='D. NANANG'!E9 -> 4900000 | Q18: =J18-L18 -> 4600000
A19: 14 | B19: DESAIN ARIEF JOMBANG | C19: ='D. ARIEF JOMBANG'!D24 -> 8271000 | D19: ='D. ARIEF JOMBANG'!F24 -> 700000 | E19: =C19-D19 -> 7571000 | F19: ='D. ARIEF JOMBANG'!D24 -> 8271000 | G19: =J19-F19 -> 2430000 | I19: 0.5 | J19: ='D. ARIEF JOMBANG'!D10 -> 10701000 | L19: =SUM(M19:P19) -> 700000 | M19: ='D. ARIEF JOMBANG'!E10 -> 0 | P19: ='D. ARIEF JOMBANG'!F22 -> 700000 | Q19: =J19-L19 -> 10001000
A20: 15 | B20: DESAIN IBU LINDA | C20: ='D. LINDA'!D22 -> 12000000 | D20: ='D. LINDA'!F22 -> 46000 | E20: =C20-D20 -> 11954000 | F20: ='D. LINDA'!D22 -> 12000000 | G20: =J20-F20 -> 12000000 | I20: 0.5 | J20: ='D. LINDA'!D9 -> 24000000 | L20: =SUM(M20:P20) -> 46000 | M20: ='D. LINDA'!E9 -> 0 | P20: ='D. LINDA'!F20 -> 46000 | Q20: =J20-L20 -> 23954000
A21: 16 | B21: DESAIN BPK SIGIT GEDANGAN | C21: ='D. SIGIT GEDANGAN'!D22 -> 6500000 | D21: ='D. SIGIT GEDANGAN'!F22 -> 119000 | E21: =C21-D21 -> 6381000 | F21: ='D. SIGIT GEDANGAN'!D22 -> 6500000 | G21: =J21-F21 -> 6500000 | I21: 0.5 | J21: ='D. SIGIT GEDANGAN'!D9 -> 13000000 | L21: =SUM(M21:P21) -> 119000 | M21: ='D. SIGIT GEDANGAN'!E9 -> 0 | P21: ='D. SIGIT GEDANGAN'!F20 -> 119000 | Q21: =J21-L21 -> 12881000
A22: 17 | B22: INTERIOR FRIZQI | C22: ='INTERIOR FRIZQI'!D26 -> 50000000 | D22: ='INTERIOR FRIZQI'!F26 -> 10208000 | E22: =C22-D22 -> 39792000 | F22: ='INTERIOR FRIZQI'!D26 -> 50000000 | G22: =J22-F22 -> 8417180 | I22: 0.5 | J22: ='INTERIOR FRIZQI'!D9 -> 58417180 | L22: =SUM(M22:P22) -> 41109000 | M22: ='INTERIOR FRIZQI'!E9 -> 40901000 | P22: ='INTERIOR FRIZQI'!F24 -> 208000 | Q22: =J22-L22 -> 17308180
A23: 18 | B23: RICKY | C23: =RICKY!D31 -> 371250000 | D23: =RICKY!F31 -> 91612000 | E23: =C23-D23 -> 279638000 | F23: =RICKY!D31 -> 371250000 | G23: =J23-F23 -> 405750000 | I23: 0.3 | J23: =RICKY!D9 -> 777000000 | L23: =SUM(M23:P23) -> 650500000 | M23: =RICKY!E9 -> 630000000 | P23: =RICKY!F29+(4000000*5) -> 20500000 | Q23: =J23-L23 -> 126500000
A24: 19 | B24: IPUT | C24: =IPUT!D26 -> 267618050 | D24: =IPUT!F26 -> 144415100 | E24: =C24-D24 -> 123202950 | F24: =IPUT!D26 -> 267618050 | G24: =J24-F24 -> 497004950 | I24: 0.25 | J24: =IPUT!D9 -> 764623000 | L24: =SUM(M24:P24) -> 480415100 | M24: =IPUT!E9 -> 460000000 | P24: =IPUT!F24+(4000000*5) -> 20415100 | Q24: =J24-L24 -> 284207900
A25: 20 | B25: DESAIN DR MOLIS | C25: ='D. DR MOLIS'!D22 -> 9000000 | D25: ='D. DR MOLIS'!F22 -> 279000 | E25: =C25-D25 -> 8721000 | F25: ='D. DR MOLIS'!D22 -> 9000000 | G25: =J25-F25 -> 9000000 | I25: 0.25 | J25: ='D. DR MOLIS'!D9 -> 18000000 | L25: =SUM(M25:P25) -> 279000 | M25: ='D. DR MOLIS'!E9 -> 0 | P25: ='D. DR MOLIS'!F20 -> 279000 | Q25: =J25-L25 -> 17721000
A26: 21 | B26: DESAIN JONI | C26: ='D. JONI'!D22 -> 6000000 | D26: ='D. JONI'!F22 -> 0 | E26: =C26-D26 -> 6000000 | F26: ='D. JONI'!D22 -> 6000000 | G26: =J26-F26 -> 5520000 | I26: 0.25 | J26: ='D. JONI'!D9 -> 11520000 | L26: =SUM(M26:P26) -> 0 | P26: ='D. JONI'!F20 -> 0 | Q26: =J26-L26 -> 11520000
A27: 22 | B27: DESAIN NIKE | C27: ='D. NIKE'!D22 -> 13500000 | D27: ='D. NIKE'!F22 -> 333000 | E27: =C27-D27 -> 13167000 | F27: ='D. NIKE'!D22 -> 13500000 | G27: =J27-F27 -> 9000000 | I27: 0.25 | J27: ='D. NIKE'!D9 -> 22500000 | L27: =SUM(M27:P27) -> 333000 | P27: ='D. NIKE'!F20 -> 333000 | Q27: =J27-L27 -> 22167000
A28: 23 | B28: DESAIN ANGGA | C28: ='D. ANGGA'!D22 -> 2172500 | D28: ='D. ANGGA'!F22 -> 0 | E28: =C28-D28 -> 2172500 | F28: ='D. ANGGA'!D22 -> 2172500 | G28: =J28-F28 -> 2172500 | I28: 0.25 | J28: ='D. ANGGA'!D9 -> 4345000 | L28: =SUM(M28:P28) -> 0 | M28: ='D. ANGGA'!E9 -> 0 | P28: ='D. ANGGA'!F20 -> 0 | Q28: =J28-L28 -> 4345000
A29: 24 | B29: DESAIN SAZA | C29: ='D. SAZA'!D22 -> 1680000 | D29: ='D. SAZA'!F22 -> 252300 | E29: =C29-D29 -> 1427700 | F29: ='D. SAZA'!D22 -> 1680000 | G29: =J29-F29 -> 1680000 | I29: 0.25 | J29: ='D. SAZA'!D9 -> 3360000 | L29: =SUM(M29:P29) -> 252300 | M29: ='D. SAZA'!E9 -> 0 | P29: ='D. SAZA'!F20 -> 252300 | Q29: =J29-L29 -> 3107700
A30: 25 | B30: IRSANDI | C30: =IRSANDI!D26 -> 138908700 | D30: =IRSANDI!F26 -> 37743900 | E30: =C30-D30 -> 101164800 | F30: =IRSANDI!D26 -> 138908700 | G30: =J30-F30 -> 257973300 | I30: 0.18 | J30: =IRSANDI!D9 -> 396882000 | L30: =SUM(M30:P30) -> 355243900 | M30: =IRSANDI!E9 -> 335000000 | P30: =IRSANDI!F24+(4000000*5) -> 20243900 | Q30: =J30-L30 -> 41638100
A31: 26 | B31: DESAIN INGE | C31: ='D. INGE'!D22 -> 1876125 | D31: ='D. INGE'!F22 -> 252300 | E31: =C31-D31 -> 1623825 | F31: ='D. INGE'!D22 -> 1876125 | G31: =J31-F31 -> 4377625 | I31: 0 | J31: ='D. INGE'!D9 -> 6253750 | L31: =SUM(M31:P31) -> 252300 | M31: ='D. INGE'!E9 -> 0 | P31: ='D. INGE'!F20 -> 252300 | Q31: =J31-L31 -> 6001450
A32: 27 | B32: LINTANG | C32: =LINTANG!D26 -> 0 | D32: =LINTANG!F26 -> 140000 | E32: =C32-D32 -> -140000 | F32: =LINTANG!D26 -> 0 | G32: =J32-F32 -> 23400000 | I32: 0 | J32: =LINTANG!D9 -> 23400000 | L32: =SUM(M32:P32) -> 20840000 | M32: =LINTANG!E9 -> 20700000 | P32: =LINTANG!F24 -> 140000 | Q32: =J32-L32 -> 2560000
A34: B | B34: OPERASIONAL
A35: 1 | B35: SALLARY | D35: =32400000*4 -> 129600000 | P35: SALLARY 2026 | Q35: =32400000*7 -> 226800000
A36: =A35+1 -> 2 | B36: TAGIHAN KANTOR | D36: =4000000*4 -> 16000000 | P36: TAGIHAN KANTOR 2026 | Q36: =4000000*7 -> 28000000
A37: =A36+1 -> 3 | B37: OPERASIONAL KANTOR | D37: =CIH!E220-CIH!N73 -> 12897100 | P37: OPERASIONAL KANTOR 2026 | Q37: =5000000*3 -> 15000000
A38: =A37+1 -> 4 | B38: OPERASIONAL PROYEK NON BSI | D38: =CIH!N75 -> 21010000 | P38: OPERASIONAL PROYEK NON BSI | Q38: =D38 -> 21010000
A39: =A38+1 -> 5 | B39: IKLAN SOSMED | D39: =CIH!M34 -> 20000000 | P39: IKLAN SOSMED 2026 | Q39: =10000000*3 -> 30000000
A41: JUMLAH | C41: =SUM(C6:C40) -> 2175711864 | D41: =SUM(D6:D40) -> 1664977488 | J41: =SUM(J6:J40) -> 4.1834557e+09 | P41: SISA MARGIN 2026 | Q41: =SUM(Q6:Q33)-(SUM(Q35:Q39)) -> 7.015506e+08
Q42: =Q41/J41 -> 0.16769643
A43: SALDO BSI | C43: =C41-D41 -> 510734376
A44: CASH IN HAND | C44: =CIH!E220-CIH!F220 -> 3119442

Sheet TF AZKA
A3: TRANSFER AZKA
A5: NO. | B5: TANGGAL | C5: KETERANGAN | D5: KODE | E5: PENERIMAAN | F5: PENGELUARAN | G5: NOTE
E6: NOMINAL | F6: NOMINAL
B7: 46290 | C7: Transfer pak Azka | E7: 80000000
B8: 46291 | C8: Pelunasan DP vendor | D8: IRSANDI | F8: =IRSANDI!F19 -> 3500000 | G8: Kohar
B9: 46291 | C9: Pelunasan DP vendor PU lanscape | D9: BALAI PU | F9: ='balai PU'!F60 -> 7500000 | G9: Kohar
B10: 46291 | C10: Pelunasan vendor progres 100% | D10: GUDANG JENNY | F10: ='GUDANG JENNY'!F20 -> 6265000 | G10: Kohar
B11: 46291 | C11: Pelunasan vendor progres 100% | D11: NUR EFENDI | F11: ='NUR EFENDI'!F19 -> 6000000 | G11: Kohar
B12: 46291 | C12: Pelunasan vendor PU lantai 2 progres 100% | D12: BALAI PU | F12: ='balai PU'!F61 -> 9815000 | G12: Sodin
B13: 46291 | C13: Kasbon vendor PU Lantai 1 progres 100% | D13: BALAI PU | F13: ='balai PU'!F62 -> 20000000 | G13: Tarmono - ainun
B14: 46291 | C14: kasbon vendor PU Bali progres 90% | D14: BALAI PU | F14: ='balai PU'!F63 -> 20000000 | G14: Shodiq
B15: 46291 | C15: Iklan IG AKP | D15: CIH | F15: =CIH!M21 -> 2000000 | G15: IG
B16: 46290 | C16: Kas + pelunasan Minus | D16: CIH | F16: =CIH!E169 -> 4920000 | G16: KAS IN HAND
B18: 46298 | C18: Transfer pak Azka | E18: 40000000
B19: 46298 | C19: Iklan IG AKP | D19: CIH | F19: =CIH!M23 -> 2000000 | G19: IG
B20: 46298 | C20: kasbon vendor PU Bali progres 95% | D20: BALAI PU | F20: ='balai PU'!F67 -> 20000000 | G20: Shodiq
B21: 46298 | C21: kasbon vendor PU lanscape progres 25% | D21: BALAI PU | F21: ='balai PU'!F65 -> 12000000 | G21: Kohar
B22: 46298 | C22: Kasbon vendor PU Lantai 1 progres 100% | D22: BALAI PU | F22: ='balai PU'!F66 -> 5000000 | G22: Tarmono - ainun
B23: 46298 | C23: Kasbon vendor PU Lantai 3 progres 100% | D23: BALAI PU | F23: ='balai PU'!F64 -> 1000000 | G23: Sodin
B25: 46302 | C25: Transfer pak Azka | E25: 5000000
B26: 46302 | C26: Kasbon vendor PU Lantai 3 | D26: BALAI PU | F26: ='balai PU'!F69 -> 5000000 | G26: Sodin
B28: 46305 | C28: Transfer pak Azka | E28: =100000000+60000000 -> 160000000 | G28: 100jt TF, 60jt cash syahru
B29: 46305 | C29: kasbon vendor PU lanscape progres 35% | D29: BALAI PU | F29: ='balai PU'!F70 -> 20000000 | G29: Kohar
B30: 46305 | C30: kasbon vendor progres 30% | D30: IPUT | F30: =IPUT!F21 -> 40000000 | G30: Slamet
B31: 46305 | C31: kasbon vendor PU Bali progres 100% | D31: BALAI PU | F31: ='balai PU'!F71 -> 40000000 | G31: Shodiq
B32: 46305 | C32: Kasbon vendor PU Lantai 3 progres 100% | D32: BALAI PU | F32: ='balai PU'!F72 -> 10000000 | G32: Sodin
B33: 46306 | C33: Iklan IG AKP | D33: CIH | F33: =CIH!N26 -> 2000000 | G33: IG
C34: Kas + pelunasan Minus | D34: CIH | F34: =CIH!E213 -> 6000000 | G34: KAS IN HAND
A36: JUMLAH | E36: =SUM(E7:E35) -> 285000000 | F36: =SUM(F7:F35) -> 243000000
E37: =E36-F36 -> 42000000

Sheet CIH
A3: OPERASIONAL | I3: IKLAN SOSMED
A5: NO. | B5: TANGGAL | C5: KETERANGAN | D5: KODE | E5: PENERIMAAN | F5: PENGELUARAN | G5: NOTE | I5: NO. | J5: TANGGAL | K5: KETERANGAN | L5: KODE | M5: PENERIMAAN | N5: PENGELUARAN | O5: NOTE
E6: NOMINAL | F6: NOMINAL | M6: NOMINAL | N6: NOMINAL
A7: 1 | B7: 46225 | C7: Transfer pak Azka | E7: 1000000 | I7: 1 | J7: 46222 | K7: Transfer pak Azka | M7: 2000000
A8: 2 | B8: 46204 | C8: BBM ambil booklet ibu Yuris | D8: DESAIN YURIS | F8: 30000 | I8: =I7+1 -> 2 | J8: 46223 | K8: iklan sosmed AKStudio IG | N8: 2000000
A9: 3 | B9: 46204 | C9: booklet desain ibu Yuris | D9: DESAIN YURIS | F9: 174000 | I9: =I8+1 -> 3 | J9: 46229 | K9: Transfer pak Azka | M9: 2000000
A10: 4 | B10: 46220 | C10: pulsa simpati kantor | F10: 15000 | I10: =I9+1 -> 4 | J10: 46230 | K10: iklan sosmed AKStudio IG | N10: 2000000
A11: 5 | B11: 46223 | C11: 5 Galon aqua kantor | F11: 105000 | I11: =I10+1 -> 5 | J11: 46242 | K11: Transfer pak Azka | M11: 2000000
A12: 6 | B12: 46223 | C12: perpanjangan proyekid | F12: 100000 | I12: =I11+1 -> 6 | J12: 46242 | K12: iklan sosmed AKStudio IG | N12: 2000000
A13: 7 | B13: 46224 | C13: internet 5G kantor | F13: 369300 | I13: 7 | J13: 46255 | K13: Transfer pak Azka | M13: 2000000
A14: 8 | B14: 46225 | C14: makan siang balai dng pak Azka | D14: BALAI PU | F14: 117000 | G14: 4 orang | I14: 8 | J14: 46255 | K14: iklan sosmed AKStudio IG | N14: 2000000
A15: 9 | B15: 46225 | C15: transfer kas ainun Proyek | D15: DEWI | F15: 500000 | I15: 9 | J15: 46264 | K15: Transfer pak Azka | M15: 2000000
A16: 10 | B16: 46225 | C16: minuman kantor | F16: 119300 | I16: 10 | J16: 46265 | K16: iklan sosmed AKStudio IG | N16: 2000000
A17: 11 | B17: 46225 | C17: pulsa simpati kantor | F17: 15000 | I17: 11 | J17: 46270 | K17: Transfer pak Azka | M17: 2000000
A18: 12 | B18: 46225 | C18: jilid SPK bpk Nur Efendi | D18: NUR EFENDI | F18: 30000 | I18: 12 | J18: 46273 | K18: iklan sosmed AKStudio IG | N18: 2000000
A19: 13 | B19: 46226 | C19: nomor AHS | D19: AHS | F19: 150000 | I19: 13 | J19: 46277 | K19: Transfer pak Azka | M19: 2000000
A20: 14 | B20: 46226 | C20: BBM ke PAL | D20: PAL | F20: 100000 | I20: 14 | J20: 46280 | K20: iklan sosmed AKStudio IG | N20: 2000000
A21: 15 | B21: 46227 | C21: Pulsa simpati AHS | D21: AHS | F21: 36000 | I21: 15 | J21: 46290 | K21: Transfer pak Azka | M21: 2000000
A22: 16 | B22: 46227 | C22: BBM ke PAL | D22: PAL | F22: 50000 | I22: 16 | J22: 46291 | K22: iklan sosmed AKStudio IG | N22: 2000000
A23: 17 | B23: 46228 | C23: Pembayaran E sim | D23: AHS | F23: 10000 | I23: 17 | J23: 46298 | K23: Transfer pak Azka | M23: 2000000
A24: 18 | B24: 46228 | C24: BBM ke bu dewi dan pak teddy | F24: 50000 | I24: 18 | J24: 46298 | K24: iklan sosmed AKStudio IG | N24: 2000000
A25: 19 | B25: 46228 | C25: makan siang survei | F25: 20200 | I25: 19 | J25: 46305 | K25: Transfer pak Azka | M25: 2000000
A26: 20 | B26: 46229 | C26: BBM ke Balai PU | D26: BALAI PU | F26: 50000 | J26: 46306 | K26: iklan sosmed AKStudio IG | N26: 2000000
A27: 21 | B27: 46229 | C27: makan siang & Malam Balai + Haleyora | D27: BALAI PU | F27: 48500
A28: 22 | B28: 46229 | C28: Transfer pak Azka | E28: 2700000
A29: 23 | B29: 46230 | C29: makan malam 3 orang | D29: ADD HALEYORA | F29: 36000
A30: 24 | B30: 46231 | C30: parkir pakuwon | F30: 10000
A31: 25 | B31: 46231 | C31: BBM pak jenny, hamsyah, beli sofa | D31: GUDANG JENNY | F31: 100000
A32: 26 | B32: 46231 | C32: makan siang dng pak azka | F32: 38000
A33: 27 | B33: 46232 | C33: makan siang ke balai 2 orang | D33: BALAI PU | F33: 94500
A34: 28 | B34: 46233 | C34: minuman kantor | F34: 95700 | I34: JUMLAH | M34: =SUM(M7:M33) -> 20000000 | N34: =SUM(N7:N33) -> 20000000
A35: 29 | B35: 46233 | C35: BBM survei filtrona + Ardian | F35: 50000
A36: 30 | B36: 46233 | C36: perpanjangan google drive + gemini AI | F36: 342990 | I36: TOTAL OPERASIONAL PROYEK
A37: 31 | B37: 46234 | C37: Penggantian tali sling | D37: HANGGAR BALAI | F37: 451500
A38: 32 | B38: 46234 | C38: gosend tali sling | D38: HANGGAR BALAI | F38: 24000 | I38: NO. | J38: TANGGAL | K38: KETERANGAN | L38: KODE | M38: PENERIMAAN | N38: PENGELUARAN | O38: NOTE
A39: 33 | B39: 46234 | C39: rembush pengeluaran inayah | F39: 176900 | M39: NOMINAL | N39: NOMINAL
A40: 34 | B40: 46235 | C40: pulsa simpati kantor | F40: 15000 | I40: 1 | K40: BALAI PU | L40: 1 | N40: =SUMIF(D7:D219,K40,F7:F219) -> 2185600
A41: 35 | B41: 46235 | C41: minuman bertemu pak Azka + mutiara | F41: =61000+179600 -> 240600 | I41: =I40+1 -> 2 | K41: NUR EFENDI | L41: 1 | N41: =SUMIF(D7:D219,K41,F7:F219) -> 218000
A42: 36 | B42: 46235 | C42: booster tandon bu dewi | D42: DEWI | F42: 1000000 | I42: =I41+1 -> 3 | K42: AHS | N42: =SUMIF(D7:D219,K42,F7:F219) -> 473000
A43: 37 | B43: 46236 | C43: pelindung layar + sarung iphone + braket | F43: 284000 | I43: =I42+1 -> 4 | K43: PAL | N43: =SUMIF(D7:D219,K43,F7:F219) -> 564000
A44: 38 | B44: 46237 | C44: BBM ke sda citra garden, Balai PU | D44: BALAI PU | F44: 100000 | I44: =I43+1 -> 5 | K44: ADD HALEYORA | N44: =SUMIF(D7:D219,K44,F7:F219) -> 36000
A45: 39 | B45: 46237 | C45: parkir ke gramedia stampel | D45: BALAI PU | F45: =10000+7000+5000 -> 22000 | I45: =I44+1 -> 6 | K45: GUDANG JENNY | L45: 1 | N45: =SUMIF(D7:D219,K45,F7:F219) -> 200000
A46: 40 | B46: 46237 | C46: perpanjangan proyekid pak ricky | D46: RICKY | F46: 100000 | I46: 7 | K46: HANGGAR BALAI | N46: =SUMIF(D7:D219,K46,F7:F219) -> 475500
A47: 41 | B47: 46237 | C47: makan siang survei citra garden 2 orang | D47: ABOEL BASUKI | F47: =47000+20000 -> 67000 | I47: 8 | K47: DEWI | N47: =SUMIF(D7:D219,K47,F7:F219) -> 1500000
A48: 42 | B48: 46238 | C48: Transfer pak Azka | E48: 2000000 | I48: 9 | K48: RICKY | L48: 1 | N48: =SUMIF(D7:D219,K48,F7:F219) -> 500000
A49: 43 | B49: 46238 | C49: Makan siang sosmed pak syahru 3 orang | F49: 70000 | I49: 10 | K49: ABOEL BASUKI | N49: =SUMIF(D7:D219,K49,F7:F219) -> 3179500
A50: 44 | B50: 46238 | C50: Stampel | D50: BALAI PU | F50: 75000 | I50: 11 | K50: TOMORO SITUBONDO | N50: =SUMIF(D7:D219,K50,F7:F219) -> 1060000
A51: 45 | B51: 46238 | C51: 4 galon kantor | F51: 85000 | I51: 12 | K51: FAUZAN SOLO | N51: =SUMIF(D7:D219,K51,F7:F219) -> 6000000
A52: 46 | B52: 46238 | C52: materai 50 lembar | F52: 502500 | I52: 13 | K52: PU MADIUN | N52: =SUMIF(D7:D219,K52,F7:F219) -> 12000
A53: 47 | B53: 46238 | C53: minuman sosmed | F53: 10000 | I53: 14 | K53: PROYEKID | N53: =SUMIF(D7:D219,K53,F7:F219) -> 7000000
A54: 48 | B54: 46239 | C54: minuman keliling sosmed pak azka | F54: =54000+7700 -> 61700 | I54: 15 | K54: IPUT | L54: 1 | N54: =SUMIF(D7:D219,K54,F7:F219) -> 415100
A55: 49 | B55: 46272 | C55: BBM bertemu dr Molis di RS Oetomo | D55: DESAIN MOLIS | F55: 80000 | I55: 16 | K55: DESAIN ARIEF | L55: 1 | N55: =SUMIF(D7:D219,K55,F7:F219) -> 700000
A56: 50 | B56: 46272 | C56: makan siang bertemu dr Molis | D56: DESAIN MOLIS | F56: 47000 | I56: 17 | K56: DESAIN DEWI | L56: 1 | N56: =SUMIF(D7:D219,K56,F7:F219) -> 9500
A57: 51 | B57: 46241 | C57: minuman aqua tanggung 2 krat | F57: 49000 | I57: 18 | K57: DESAIN YURIS | N57: =SUMIF(D7:D219,K57,F7:F219) -> 204000
A58: 52 | B58: 46241 | C58: makan siang bertemu pak rizky PU | D58: BALAI PU | F58: 25000 | I58: 19 | K58: DESAIN MOLIS | L58: 1 | N58: =SUMIF(D7:D219,K58,F7:F219) -> 279000
A59: 53 | B59: 46241 | C59: BBM ke PU, PAL antar cat | D59: PAL | F59: 100000 | I59: 20 | K59: DESAIN SIGIT GELURAN | L59: 1 | N59: =SUMIF(D7:D219,K59,F7:F219) -> 119000
A60: 54 | B60: 46241 | C60: Pulsa simpati kantor | F60: 15000 | I60: 21 | K60: DESAIN LINDA | L60: 1 | N60: =SUMIF(D7:D219,K60,F7:F219) -> 46000
A61: 55 | B61: 46241 | C61: survei Situbondo pak azka | E61: 1000000 | I61: 22 | K61: DESAIN ERLIS | L61: 1 | N61: =SUMIF(D7:D219,K61,F7:F219) -> 50000
A62: 56 | B62: 46241 | C62: survei Situbondo pak azka | D62: TOMORO SITUBONDO | F62: 1000000 | I62: 23 | K62: SYAHRU | N62: =SUMIF(D7:D219,K62,F7:F219) -> 381000
A63: 57 | B63: 46241 | C63: sumur bor air tanah bpk Fauzan solo | E63: 4000000 | I63: 24 | K63: IRSANDI | L63: 1 | N63: =SUMIF(D7:D219,K63,F7:F219) -> 243900
A64: 58 | B64: 46241 | C64: sumur bor air tanah bpk Fauzan solo | D64: FAUZAN SOLO | F64: 4000000 | I64: 25 | K64: INTERIOR FRIZQI | L64: 1 | N64: =SUMIF(D7:D219,K64,F7:F219) -> 208000
A65: 59 | B65: 46242 | C65: transfer pak Azka | E65: =3500000-2000000 -> 1500000 | I65: 26 | K65: DESAIN NIKE | L65: 1 | N65: =SUMIF(D7:D219,K65,F7:F219) -> 333000
A66: 60 | B66: 46242 | C66: 2 rim HVS A4 | F66: 50000 | I66: 27 | K66: JIPE | N66: =SUMIF(D7:D219,K66,F7:F219) -> 125000
A67: 61 | B67: 46243 | C67: BBM ke krian | D67: NUR EFENDI | F67: 100000 | I67: 28 | K67: DESAIN SAZA | L67: 1 | N67: =SUMIF(D7:D219,K67,F7:F219) -> 252300
A68: 62 | B68: 46243 | C68: cuci mobil avanza putih | F68: 45000 | I68: 29 | K68: DESAIN INGE | L68: 1 | N68: =SUMIF(D7:D219,K68,F7:F219) -> 113500
A69: 63 | B69: 46244 | C69: minuman bertemu dzaki tomoro | D69: TOMORO SITUBONDO | F69: 60000 | I69: 30 | K69: LINTANG | L69: 1 | N69: =SUMIF(D7:D219,K69,F7:F219) -> 140000
A70: 64 | B70: 46245 | C70: makan siang ke citra garden | D70: ABOEL BASUKI | F70: 55000
A71: 65 | B71: 46245 | C71: BBM ke citra garden | D71: ABOEL BASUKI | F71: 100000
A72: 66 | B72: 46245 | C72: etoll citra garden | D72: ABOEL BASUKI | F72: =12500+4000+12500+6000 -> 35000
A73: 67 | B73: 46245 | C73: 4 galon kantor | F73: 80000 | I73: JUMLAH | M73: =SUM(M40:M72) -> 0 | N73: =SUM(N40:N72) -> 27022900
A74: 68 | B74: 46245 | C74: pelunasan sumur bor bpk Fauzan solo | E74: 2000000 | J74: OPERASIONAL PROYEK BSI | L74: 1 | N74: =SUMIF(L40:L72,L74,N40:N72) -> 6012900
A75: 69 | B75: 46245 | C75: pelunasan sumur bor bpk Fauzan solo | D75: FAUZAN SOLO | F75: 2000000 | J75: OPERASIONAL PROYEK DILUAR BSI | N75: =N73-N74 -> 21010000
A76: 70 | B76: 46246 | C76: makan siang 3 orang bertemu pak rizky PU | D76: BALAI PU | F76: 67000
A77: 71 | B77: 46246 | C77: paket dokumen PU Madiun | D77: PU MADIUN | F77: 12000
A78: 72 | B78: 46246 | C78: pulsa simpati kantor | F78: 26500
A79: 73 | B79: 46247 | C79: Service update Proyekid | E79: 2000000
A80: 74 | B80: 46247 | C80: Service update Proyekid | D80: PROYEKID | F80: 2000000
A81: 75 | B81: 46247 | C81: BBM ke pak iput geluran + agus+ balai PU | D81: IPUT | F81: 100000
A82: 76 | B82: 46247 | C82: minuman ke pak iput | D82: IPUT | F82: 3600
A83: 77 | B83: 46248 | C83: tiang + bendera kantor | F83: 90000
A84: 78 | B84: 46249 | C84: etoll citra garden | D84: ABOEL BASUKI | F84: 50000
A85: 79 | B85: 46249 | C85: perpanjangan centang biru IG AKP | F85: 122100
A86: 80 | B86: 46252 | C86: pembayaran indihome 4G/5G | F86: 369300
A87: 81 | B87: 46252 | C87: 3 galon aqua | F87: 65000
A88: 82 | B88: 46253 | C88: BBM ke Balai PU | D88: BALAI PU | F88: 50000
A89: 83 | B89: 46253 | C89: makan siang 2 orang ke balai PU | D89: BALAI PU | F89: 58000
A90: 84 | B90: 46255 | C90: Transfer pak Azka | E90: 1500000
A91: 85 | B91: 46255 | C91: fotocopy compro | F91: 200000
A92: 86 | B92: 46255 | C92: makan malam lembur denny + anak magang | D92: PAL | F92: 72000
A93: 87 | B93: 46256 | C93: obat-obatan kantor | F93: 31278
A94: 88 | B94: 46256 | C94: makan siang team arsitek lembur | D94: PAL | F94: 142000
A95: 89 | B95: 46257 | C95: bbm bertemu klien Dr Molis | D95: DESAIN MOLIS | F95: 50000
A96: 90 | B96: 46257 | C96: bbm deni bertemu DR molis | D96: DESAIN MOLIS | F96: 50000
A97: 91 | B97: 46257 | C97: DP brosur proyek perumj bpk Arief | D97: DESAIN ARIEF | F97: 350000
A98: 92 | B98: 46258 | C98: Proyekid bpk Iput | D98: IPUT | F98: 100000
A99: 93 | B99: 46258 | C99: makan siang 3 orang presentasi balai PU Aula | D99: BALAI PU | F99: 73000
A100: 94 | B100: 46258 | C100: stampel Akstudio baru + cemilan kantor | F100: 100000
A101: 95 | B101: 46258 | C101: zoom konsultasi desain bu dewi | D101: DESAIN DEWI | F101: 9500
A102: 96 | B102: 46259 | C102: paket simapati AHS | D102: AHS | F102: 15000
A103: 97 | B103: 46260 | C103: minuman ke pak iput | D103: IPUT | F103: 13500
...

Sheet balai PU
A1: PROYEK INTERIOR BALAI BESAR PU
B4: NO | C4: KET | D4: RAB incl ppn | E4: PPN | F4: PPH 1,75 % | G4: RAP SUBKON | H4: ADD SUBKON | I4: LAIN-LAIN | J4: FEE | K4: LABA | L4: % LABA
B5: 1 | C5: SPK LANTAI 2 | D5: 399340000 | E5: 39574400 | F5: =(D5-E5)*1.75% -> 6295898 | G5: 238700000 | H5: 16115000 | J5: =28000000+18000000 -> 46000000 | K5: =D5-E5-F5-G5-J5-H5 -> 52654702 | L5: =K5/(D5-E5)*100 -> 14.635836
B6: 2 | C6: SPK LANTAI 3 | D6: 394714000 | E6: 39115890 | F6: =(D6-E6)*1.75% -> 6222966.9 | G6: 201000000 | H6: 42122000 | I6: =27192800*0 -> 0 | J6: =28000000+18000000 -> 46000000 | K6: =D6-E6-F6-G6-J6-H6-I6 -> 60253143 | L6: =K6/(D6-E6)*100 -> 16.944169
B7: 3 | C7: SPK LANTAI 1 | D7: 398400000 | E7: =D7-D7/1.11 -> 39481081 | F7: =(D7-E7)*1.75% -> 6281081.1 | G7: 241000000 | J7: 46000000 | K7: =D7-E7-F7-G7-J7 -> 65637838 | L7: =K7/(D7-E7)*100 -> 18.287651
B8: 4 | C8: SPK 1 LOBBY BALI | D8: 199209480 | E8: 19741480 | F8: =(D8-E8)*1.75% -> 3140690 | G8: 123634520 | I8: =(D8-E8-F8)*1.5% -> 2644909.6 | J8: =12000000+((D8-E8-F8)*2.5%) -> 16408183 | K8: =D8-E8-F8-G8-I8-J8 -> 33639698 | L8: =K8/(D8-E8)*100 -> 18.74412
B9: 5 | C9: SPK RUANG MEETING LUAR KPIJ | D9: 49931000 | E9: 4948207 | F9: =(D9-E9)*1.75% -> 787198.88 | G9: =8506000+18200688+1700000 -> 28406688 | J9: 4000000 | K9: =D9-E9-F9-G9-J9-H9 -> 11788906 | L9: =K9/(D9-E9)*100 -> 26.20759
B10: 6 | C10: SPK 2 KASATKER BALI | D10: 192561000 | E10: =D10-D10/1.11 -> 19082622 | F10: =(D10-E10)*1.75% -> 3035871.6 | G10: 133745060 | J10: =(6000000*2)+((D10-E10-F10)*2.5%) -> 16261063 | K10: =D10-E10-F10-G10-I10-J10 -> 20436384 | L10: =K10/(D10-E10)*100 -> 11.780364
B11: 7 | C11: SPK LANSCAPE | D11: =197097150+194621850 -> 391719000 | E11: =D11-D11/1.11 -> 38819000 | F11: =(D11-E11)*1.75% -> 6175750 | G11: 175000000 | J11: 46000000 | K11: =D11-E11-F11-G11-I11-J11 -> 1.2572425e+08 | L11: =K11/(D11-E11)*100 -> 35.626027
L12: 0
C13: TOTAL | D13: =SUM(D5:D12) -> 2025874480 | E13: =SUM(E5:E12) -> 2.0076268e+08 | F13: =SUM(F5:F12) -> 31939457 | G13: =SUM(G5:G12) -> 1141486268 | H13: =SUM(H5:H12) -> 58237000 | I13: =SUM(I5:I12) -> 2644909.6 | J13: =SUM(J5:J12) -> 2.2066925e+08 | K13: =SUM(K5:K12) -> 3.7013492e+08 | L13: =K13/(D13-E13)*100 -> 20.280123
N16: KAS SURVEI BALAI BESAR BALI
A17: NO. | B17: KET | C17: PENERIMAAN | E17: PENGELUARAN | G17: KETERANGAN
C18: TANGGAL | D18: NOMINAL | E18: TANGGAL | F18: NOMINAL | M18: NO | N18: TANGGAL | O18: KET | P18: KAS
A19: 1 | B19: T1 SUBKON LANTAI 2 | E19: 46171 | F19: 50000000 | G19: SUBKON SODIN | P19: DEBIT | Q19: KREDIT
A20: =A19+1 -> 2 | B20: T1 SUBKON LANTAI 2 | E20: 46182 | F20: 20000000 | G20: SUBKON SODIN | N20: 46201 | O20: KAS | P20: 5000000
A21: =A20+1 -> 3 | B21: T1 SUBKON LANTAI 3 | E21: 46190 | F21: 25000000 | G21: SUBKON SODIN | N21: 46201 | O21: 2 tiket pesawat surabaya - bali | Q21: 1669400
A22: =A21+1 -> 4 | B22: T1 SUBKON LANTAI 3 | E22: 46193 | F22: 38000000 | G22: SUBKON SODIN | N22: 46203 | O22: Gojek ke airport Juanda | Q22: 119000
A23: =A22+1 -> 5 | B23: SURVEI BALI | E23: 46201 | F23: 5000000 | G23: BAKIR | N23: 46203 | O23: Konsumsi penerbangan | Q23: 60500
A24: =A23+1 -> 6 | B24: T2 SUBKON LANTAI 2 | E24: 46202 | F24: 20000000 | G24: SUBKON SODIN | N24: 46203 | O24: gojek bandara ke PU bali + parkir | Q24: 112000
A25: 7 | B25: T1 SPK LANTAI 2 | C25: 46176 | D25: 211786156 | N25: 46203 | O25: konsumsi PU | Q25: 67000
A26: 8 | B26: T2 SUBKON LANTAI 2 | E26: 46180 | F26: 50000000 | G26: SUBKON SODIN | N26: 46203 | O26: tiket hotel 1 hari | Q26: 265540
A27: 9 | B27: SALLARY DRAWING | E27: 46204 | F27: 2140000 | G27: AFIF | N27: 46203 | O27: makan siang 2 orang | Q27: 55999
A28: 10 | B28: T1 SUBKON LANTAI 1 | E28: 46214 | F28: 30000000 | G28: SUBKON AINUN | N28: 46203 | O28: konsumsi bertemu tim interior | Q28: 50500
A29: 11 | B29: T1 SPK LANTAI 3 | C29: 46219 | D29: 139531958 | N29: 46203 | O29: tiket hotel team interior 1 hari | Q29: 400000
A30: 12 | B30: T1 SUBKON LANTAI 1 | E30: 46223 | F30: 30000000 | G30: SUBKON AINUN | N30: 46203 | O30: konsumsi team | Q30: 159000
A31: 13 | B31: T3 SUBKON LANTAI 2 | E31: 46223 | F31: 38000000 | G31: SUBKON SODIN | N31: 46203 | O31: sewa motor 2 hari | Q31: 150000
A32: 14 | B32: T3 SUBKON LANTAI 2 | E32: 46229 | F32: 17000000 | G32: SUBKON SODIN | N32: 46203 | O32: makan malam 2 orang | Q32: 104000
A33: 15 | B33: T1 SUBKON LANTAI 1 | E33: 46229 | F33: 12300000 | G33: SUBKON AINUN | N33: 46174 | O33: konsumsi team | Q33: 10900
A34: 16 | B34: T2 SPK LANTAI 2 | C34: 46232 | D34: 141190770 | N34: 46174 | O34: 2 tiket pesawat bali - sby | Q34: 1561400
A35: 17 | B35: FEE SPK LANTAI 2 | E35: 46232 | F35: =28000000+18000000 -> 46000000 | G35: FEE PU | N35: 46174 | O35: makan siang 2 orang | Q35: 76000
A36: 18 | B36: SALLARY DRAWING | E36: 46235 | F36: 4000000 | G36: AFIF | N36: 46174 | O36: taxi ke kantor | Q36: 130000
A37: 19 | B37: T2 SUBKON LANTAI 3 | E37: 46235 | F37: 25000000 | G37: SUBKON SODIN
A38: 20 | B38: DP SUBKON BALI | E38: 46237 | F38: 40000000 | G38: SUBKON SHODIQ
A39: 21 | B39: T2 SUBKON LANTAI 3 | E39: 46238 | F39: 26500000 | G39: SUBKON SODIN | N39: JUMLAH | P39: =SUM(P20:P38) -> 5000000 | Q39: =SUM(Q20:Q38) -> 4991239
A40: 22 | B40: LUNAS SEKAT MEETING | E40: 46247 | F40: 8506000 | G40: SUBKON HERMAN
A41: 23 | B41: T2 SPK LANTAI 3 | C41: 46248 | D41: 139531958 | N41: SALDO | P41: =P39-Q39 -> 8761
A42: 24 | B42: T3 SPK LANTAI 3 | C42: 46253 | D42: 69765980
A43: 25 | B43: FEE SPK LANTAI 3 | E43: 46253 | F43: =28000000+18000000 -> 46000000 | G43: FEE PU
A44: 26 | B44: T3 SUBKON LANTAI 2 | E44: 46255 | F44: 30000000 | G44: SUBKON SODIN
A45: 27 | B45: T3 SUBKON LANTAI 3 | E45: 46255 | F45: 50000000 | G45: SUBKON SODIN
A46: 28 | B46: T1 SUBKON R MEETING | E46: 46255 | F46: 9100000 | G46: SUBKON MJM DEKORATION
A47: 29 | B47: T2 SUBKON LANTAI 1 | E47: 46259 | F47: 40000000 | G47: SUBKON AINUN
A48: 30 | B48: T1 SPK LANTAI 1 | C48: 46265 | D48: 176169295
A49: 31 | B49: SALLARY DRAWING | E49: 46266 | F49: 4000000 | G49: AFIF
A50: 32 | B50: KASBON SUBKON BALI | E50: 46270 | F50: 30000000 | G50: SUBKON SHODIQ
A51: 33 | B51: KASBON SPK LANTAI 3 | E51: 46270 | F51: 50000000 | G51: SUBKON SODIN
A52: 34 | B52: KASBON SPK LANSCAPE | E52: 46277 | F52: 10000000 | G52: SUBKON KOHAR
A53: 35 | B53: KASBON T2 SUBKON R MEETING | E53: 46277 | F53: 5000000 | G53: SUBKON MJM DEKORATION
A54: 36 | B54: KASBON SUBKON BALI | E54: 46280 | F54: 10000000 | G54: SUBKON SHODIQ
A55: 37 | B55: SPK RUANG MEETING LUAR KPIJ | C55: 46283 | D55: 44195797
A56: 38 | B56: KASBON SUBKON LANTAI 2 | E56: 46284 | F56: 20000000 | G56: SUBKON SODIN
A57: 39 | B57: FEE SPK LANTAI 1 | E57: 46284 | F57: =28000000+18000000 -> 46000000 | G57: FEE PU
A58: 40 | B58: FEE SPK RUANG MEETING LUAR KPIJ | E58: 46284 | F58: 4000000 | G58: FEE PU
A59: 41 | B59: PELUNASAN SUBKON R MEETING | E59: 46287 | F59: 4100688 | G59: SUBKON MJM DEKORATION
A60: 42 | B60: PELUNASAN DP LANSCAPE | E60: 46291 | F60: 7500000 | G60: SUBKON KOHAR
A61: 43 | B61: PELUNASAN SPK LANTAI 2 | E61: 46291 | F61: 9815000 | G61: SUBKON SODIN
A62: 44 | B62: KASBON SPK LANTAI 1 | E62: 46291 | F62: 20000000 | G62: SUBKON AINUN
A63: 45 | B63: KASBON SUBKON BALI | E63: 46291 | F63: 20000000 | G63: SUBKON SHODIQ
A64: 46 | B64: KASBON SPK LANTAI 3 | E64: 46298 | F64: 1000000 | G64: SUBKON SODIN
A65: 47 | B65: KASBON SPK LANSCAPE | E65: 46298 | F65: 12000000 | G65: SUBKON KOHAR
A66: 48 | B66: KASBON SPK LANTAI 1 | E66: 46298 | F66: 5000000 | G66: SUBKON AINUN
A67: 49 | B67: KASBON SUBKON BALI | E67: 46298 | F67: 20000000 | G67: SUBKON SHODIQ
A68: 50 | B68: T2 SPK LANTAI 1 | C68: 46302 | D68: 176000000
B69: KASBON SPK LANTAI 3 | E69: 46302 | F69: 5000000 | G69: SUBKON SODIN
B70: KASBON SPK LANSCAPE | E70: 46306 | F70: 20000000 | G70: SUBKON KOHAR
B71: KASBON SUBKON BALI | E71: 46306 | F71: 40000000 | G71: SUBKON SHODIQ
B72: KASBON SPK LANTAI 3 | E72: 46306 | F72: 10000000 | G72: SUBKON SODIN
B74: BIAYA OPERASIONAL | F74: =CIH!N40 -> 2185600
A76: JUMLAH | D76: =SUM(D19:D75) -> 1098171914 | F76: =SUM(F19:F75) -> 1018147288
B80: TOTAL PEMBAYARAN KE VENDOR
A81: NO. | B81: KET | C81: NAMA VENDOR | D81: TERBAYAR | E81: KURANG BAYAR | F81: REKENING | G81: REKENING ATAS NAMA
A83: 1 | B83: SPK 1 LANTAI 2 | C83: SODIN | D83: =F19+F20+F24+F26+F31+F32+F44+F56+F61 -> 254815000 | E83: =G5+H5-D83 -> 0 | F83: BCA | G83: 1410646397
A84: =A83+1 -> 2 | B84: SPK 2 LANTAI 3 | C84: SODIN | D84: =F21+F22+F37+F39+F45+F51+F64+F69+F72 -> 230500000 | E84: =G6+H6-D84 -> 12622000 | F84: BCA | G84: 1410646397
A85: =A84+1 -> 3 | B85: SPK 3 LANTAI 1 | C85: TARMONO | D85: =F28+F30+F33+F47+F62+F66 -> 137300000 | E85: =G7+H7-D85 -> 103700000 | F85: BCA | G85: 1840253453
A86: =A85+1 -> 4 | B86: SPK 4 BALI | C86: SHODIQ | D86: =F38+F50+F54+F63+F67+F71 -> 160000000 | E86: =G8+H8+G10+H10-D86 -> 97379580 | F86: BCA | G86: 0310438880
A87: =A86+1 -> 5 | B87: SPK 5 R. MEETING KPIJ | C87: AINUN | D87: =F40+F46+F53+F59 -> 26706688 | E87: =G9+H9-D87 -> 1700000
A88: =A87+1 -> 6 | B88: SPK LANSCAPE BALAI PU | C88: KOHAR | D88: =F52+F60+F65+F70 -> 49500000 | E88: =G11+H11-D88 -> 125500000

Sheet ford
A1: DANA PROYEK PROYEK DEALEAR FORD
B4: NO | C4: KET | D4: RAB | E4: RAP SUBKON | F4: FEE | G4: LABA | H4: % LABA
C5: SPK | D5: 20000000 | E5: 17500000 | F5: 1250000 | G5: =D5-E5-F5 -> 1250000 | H5: =G5/D5*100 -> 6.25
H8: 0
C9: TOTAL | D9: =SUM(D5:D8) -> 20000000 | E9: =SUM(E5:E8) -> 17500000 | F9: =SUM(F5:F8) -> 1250000 | G9: =SUM(G5:G8) -> 1250000 | H9: =SUM(H5:H8) -> 6.25
A12: NO. | B12: KET | C12: PENERIMAAN | E12: PENGELUARAN SUBKON YUDI
C13: TANGGAL | D13: NOMINAL | E13: TANGGAL | F13: NOMINAL
A14: 1 | B14: DP | C14: 46153 | D14: 10000000 | E14: 46153 | F14: 7500000
A15: =A14+1 -> 2 | B15: TERMIN I | C15: 46172 | D15: 8000000
A16: =A15+1 -> 3 | B16: T I VENDOR | E16: 46173 | F16: 8000000
A17: =A16+1 -> 4 | B17: RETENSI CASH | C17: 46225 | D17: 2000000
A18: =A17+1 -> 5 | B18: FEE | E18: 46225 | F18: 1250000
B19: T2 VENDOR | E19: 46233 | F19: 2000000
A22: JUMLAH | D22: =SUM(D14:D21) -> 20000000 | F22: =SUM(F14:F21) -> 18750000
A23: KURANG BAYAR | D23: =D5-D22 -> 0 | F23: =E9+F9-F22 -> 0

Sheet RICKY
A1: DANA PROYEK RICKY WIYUNG
B4: NO | C4: KET | D4: RAB | E4: RAP SUBKON | F4: FEE | G4: LABA | H4: % LABA
C5: SPK | D5: 777000000 | E5: 630000000 | G5: =D5-E5-F5 -> 147000000 | H5: =G5/D5*100 -> 18.918919
H8: 0
C9: TOTAL | D9: =SUM(D5:D8) -> 777000000 | E9: =SUM(E5:E8) -> 630000000 | G9: =SUM(G5:G8) -> 147000000 | H9: =SUM(H5:H8) -> 18.918919
A12: NO. | B12: KET | C12: PENERIMAAN | E12: PENGELUARAN | G12: KETERANGAN
C13: TANGGAL | D13: NOMINAL | E13: TANGGAL | F13: NOMINAL
A14: 1 | B14: DP | C14: 46165 | D14: 77000000
A15: =A14+1 -> 2 | B15: TERMIN I | C15: 46189 | D15: 50000000
A16: =A15+1 -> 3 | B16: TERMIN I | C16: 46190 | D16: 100000000
A17: =A16+1 -> 4 | B17: TERMIN I | C17: 46202 | D17: 44250000
A18: =A17+1 -> 5 | B18: VENDOR | E18: 46211 | F18: 15000000
A19: =A18+1 -> 6 | B19: VENDOR | E19: 46228 | F19: 40000000
A20: =A19+1 -> 7 | B20: SALARY PENGAWAS | E20: 46235 | F20: 4000000 | G20: SALARY AGUNG
A21: =A20+1 -> 8 | B21: VENDOR | E21: 46265 | F21: 24112000 | G21: diambil dr Proyek madiun
A22: =A21+1 -> 9 | B22: SALARY PENGAWAS | E22: 46266 | F22: 4000000 | G22: SALARY AGUNG
A23: 10 | B23: TERMIN II | C23: 46291 | D23: =50000000+50000000 -> 100000000
B24: SALARY PENGAWAS | E24: 46296 | F24: 4000000 | G24: SALARY AGUNG
B29: OPERASIONAL | F29: =CIH!N48 -> 500000
A31: JUMLAH | D31: =SUM(D14:D30) -> 371250000 | F31: =SUM(F14:F30) -> 91612000
A32: KURANG BAYAR VENDOR | D32: =D5-D31 -> 405750000 | F32: =E9-SUM(F14:F28) -> 538888000

Sheet D. SENDI RSAL
A1: PROYEK DESAIN SENDI RSAL
B4: NO | C4: KET | D4: RAB | E4: RAP SUBKON | F4: FEE | G4: LABA | H4: % LABA
C5: SPK DESAIN | D5: 4551200 | G5: =D5-E5-F5 -> 4551200 | H5: =G5/D5*100 -> 100
H8: 0
C9: TOTAL | D9: =SUM(D5:D8) -> 4551200 | E9: =SUM(E5:E8) -> 0 | G9: =SUM(G5:G8) -> 4551200 | H9: =SUM(H5:H8) -> 100
A12: NO. | B12: KET | C12: PENERIMAAN | E12: PENGELUARAN SUBKON YUDI
C13: TANGGAL | D13: NOMINAL | E13: TANGGAL | F13: NOMINAL
A14: 1 | B14: DP | C14: 46185 | D14: 2275600
A15: =A14+1 -> 2 | B15: PELUNASAN | C15: 46209 | D15: 2275600
A16: =A15+1 -> 3
A17: =A16+1 -> 4
A18: =A17+1 -> 5
A22: JUMLAH | D22: =SUM(D14:D21) -> 4551200 | F22: =SUM(F14:F21) -> 0
A23: KURANG BAYAR | D23: =D5-D22 -> 0 | F23: =E9-F22 -> 0

Sheet GUDANG JENNY
A1: PROYEK GUDANG JENNY
B4: NO | C4: KET | D4: RAB | E4: RAP SUBKON | F4: FEE | G4: LABA | H4: % LABA
C5: SPK ( INCL PPN + PPH) | D5: =(60087500*2)-(60087500*2*11%) -> 106955750 | E5: =65000000+1265000 -> 66265000 | G5: =D5-E5-F5 -> 40690750 | H5: =G5/D5*100 -> 38.044472
H8: 0
C9: TOTAL | D9: =SUM(D5:D8) -> 106955750 | E9: =SUM(E5:E8) -> 66265000 | G9: =SUM(G5:G8) -> 40690750 | H9: =SUM(H5:H8) -> 38.044472
A12: NO. | B12: KET | C12: PENERIMAAN | E12: PENGELUARAN SUBKON YUDI
C13: TANGGAL | D13: NOMINAL | E13: TANGGAL | F13: NOMINAL
A14: 1 | B14: DP | C14: 46190 | D14: =30043750-(30043750*11%) -> 26738938
A15: =A14+1 -> 2 | B15: DP | C15: 46190 | D15: =30043750-(30043750*11%) -> 26738938
A16: =A15+1 -> 3 | B16: DP | E16: 46197 | F16: 30000000
A17: =A16+1 -> 4 | B17: VENDOR | E17: 46214 | F17: 16800000
A18: =A17+1 -> 5 | B18: VENDOR | E18: 46221 | F18: 10000000
A19: =A18+1 -> 6 | B19: VENDOR | E19: 46222 | F19: 3200000
A20: =A19+1 -> 7 | B20: VENDOR | E20: 46291 | F20: 6265000
B23: OPERASIONAL | F23: =CIH!N45 -> 200000
A25: JUMLAH | D25: =SUM(D14:D24) -> 53477875 | F25: =SUM(F14:F24) -> 66465000
A26: KURANG BAYAR VENDOR | D26: =D5-D25 -> 53477875 | F26: =E9-SUM(F14:F22) -> 0

Sheet CANOPY DEWI
A1: PROYEK CANOPY BELAKANG DEWI
B4: NO | C4: KET | D4: RAB | E4: RAP SUBKON | F4: FEE | G4: LABA | H4: % LABA
C5: SPK | D5: 9000000 | E5: 7500000 | G5: =D5-E5-F5 -> 1500000 | H5: =G5/D5*100 -> 16.666667
H8: 0
C9: TOTAL | D9: =SUM(D5:D8) -> 9000000 | E9: =SUM(E5:E8) -> 7500000 | G9: =SUM(G5:G8) -> 1500000 | H9: =SUM(H5:H8) -> 16.666667
A12: NO. | B12: KET | C12: PENERIMAAN | E12: PENGELUARAN SUBKON YUDI
C13: TANGGAL | D13: NOMINAL | E13: TANGGAL | F13: NOMINAL
A14: 1 | B14: DP | E14: 46184 | F14: 4000000
A15: =A14+1 -> 2 | B15: LUNAS | C15: 46192 | D15: 9000000
A16: =A15+1 -> 3 | B16: T VENDOR | E16: 46193 | F16: 3500000
A17: =A16+1 -> 4
A18: =A17+1 -> 5
A22: JUMLAH | D22: =SUM(D14:D21) -> 9000000 | F22: =SUM(F14:F21) -> 7500000
A23: KURANG BAYAR | D23: =D5-D22 -> 0 | F23: =E9-F22 -> 0

Sheet JENDELA KORIDOR DEWI
A1: PROYEK JENDELA KORIDOR BU DEWI
B4: NO | C4: KET | D4: RAB | E4: RAP SUBKON | F4: FEE | G4: LABA | H4: % LABA
C5: SPK | D5: 8000000 | E5: 5330000 | G5: =D5-E5-F5 -> 2670000 | H5: =G5/D5*100 -> 33.375
G6: =D6-E6-F6 -> 0
H8: 0
C9: TOTAL | D9: =SUM(D5:D8) -> 8000000 | E9: =SUM(E5:E8) -> 5330000 | G9: =SUM(G5:G8) -> 2670000 | H9: =G9/D9*100 -> 33.375
A12: NO. | B12: KET | C12: PENERIMAAN | E12: PENGELUARAN SUBKON YUDI
C13: TANGGAL | D13: NOMINAL | E13: TANGGAL | F13: NOMINAL
A14: 1 | B14: DP VENDOR | E14: 46202 | F14: 3000000
A15: =A14+1 -> 2 | B15: SPK | C15: 46204 | D15: 8000000
A16: =A15+1 -> 3 | B16: LUNAS VENDOR | E16: 46204 | F16: 2330000
A17: =A16+1 -> 4
A18: =A17+1 -> 5
A22: JUMLAH | D22: =SUM(D14:D21) -> 8000000 | F22: =SUM(F14:F21) -> 5330000
A23: KURANG BAYAR | F23: =E9-F22 -> 0

Sheet NUR EFENDI
A1: PROYEK ATAP BPK NUR EFFENDI
B4: NO | C4: KET | D4: RAB | E4: RAP SUBKON | F4: FEE | G4: LABA | H4: % LABA
C5: SPK | D5: 65487000 | E5: 52000000 | G5: =D5-E5-F5 -> 13487000 | H5: =G5/D5*100 -> 20.594927
C6: ADD | D6: 7800000 | E6: 6000000 | G6: =D6-E6-F6 -> 1800000 | H6: =G6/D6*100 -> 23.076923
H8: 0
C9: TOTAL | D9: =SUM(D5:D8) -> 73287000 | E9: =SUM(E5:E8) -> 58000000 | G9: =SUM(G5:G8) -> 15287000 | H9: =G9/D9*100 -> 20.859088
A12: NO. | B12: KET | C12: PENERIMAAN | E12: PENGELUARAN
C13: TANGGAL | D13: NOMINAL | E13: TANGGAL | F13: NOMINAL
A14: 1 | B14: TERMIN 1 | C14: 46232 | D14: 32743500
A15: =A14+1 -> 2 | B15: DP VENDOR | E15: 46233 | F15: 25000000
A16: =A15+1 -> 3 | B16: TERMIN 2 | C16: 46267 | D16: 32743500
A17: =A16+1 -> 4 | B17: LUNAS VENDOR | E17: 46270 | F17: 27000000
A18: =A17+1 -> 5 | B18: ADD | C18: 46287 | D18: 7800000
A19: 6 | B19: ADD VENDOR | E19: 46291 | F19: 6000000
B21: OPERASIONAL | F21: =CIH!N41 -> 218000
A23: JUMLAH | D23: =SUM(D14:D22) -> 73287000 | F23: =SUM(F14:F22) -> 58218000
A24: KURANG BAYAR

Sheet IPUT
A1: PROYEK BPK IPUT
B4: NO | C4: KET | D4: RAB | E4: RAP SUBKON | F4: FEE | G4: LABA | H4: % LABA
C5: SPK | D5: 764623000 | E5: 460000000 | G5: =D5-E5-F5 -> 304623000 | H5: =G5/D5*100 -> 39.839633
G6: =D6-E6-F6 -> 0
H8: 0
C9: TOTAL | D9: =SUM(D5:D8) -> 764623000 | E9: =SUM(E5:E8) -> 460000000 | G9: =SUM(G5:G8) -> 304623000 | H9: =G9/D9*100 -> 39.839633
A12: NO. | B12: KET | C12: PENERIMAAN | E12: PENGELUARAN | G12: KETERANGAN
C13: TANGGAL | D13: NOMINAL | E13: TANGGAL | F13: NOMINAL
A14: 1 | B14: DP SPK | C14: 46241 | D14: 76462300
A15: =A14+1 -> 2 | B15: DP Bongkar | E15: 46247 | F15: 5000000
A16: =A15+1 -> 3 | B16: Pelunasan | E16: 46255 | F16: 4000000
A17: =A16+1 -> 4 | B17: DP vendor | E17: 46259 | F17: 41000000
A18: =A17+1 -> 5 | B18: DP vendor | E18: 46259 | F18: 50000000
A19: 6 | B19: TERMIN I | C19: 46260 | D19: 191155750
A20: 7 | B20: SALARY PENGAWAS | E20: 46296 | F20: 4000000 | G20: SALARY DAFA
E21: 46306 | F21: 40000000
B24: OPERASIONAL | F24: =CIH!N54 -> 415100
A26: JUMLAH | D26: =SUM(D14:D25) -> 267618050 | F26: =SUM(F14:F25) -> 144415100
A27: KURANG BAYAR | D27: =D9-D26 -> 497004950 | F27: =E5-SUM(F14:F18)-F21 -> 320000000

Sheet IRSANDI
A1: PROYEK BPK IRSANDI
B4: NO | C4: KET | D4: RAB | E4: RAP SUBKON | F4: FEE | G4: LABA | H4: % LABA
C5: SPK | D5: 396882000 | E5: 335000000 | G5: =D5-E5-F5 -> 61882000 | H5: =G5/D5*100 -> 15.59204
G6: =D6-E6-F6 -> 0
H8: 0
C9: TOTAL | D9: =SUM(D5:D8) -> 396882000 | E9: =SUM(E5:E8) -> 335000000 | G9: =SUM(G5:G8) -> 61882000 | H9: =G9/D9*100 -> 15.59204
A12: NO. | B12: KET | C12: PENERIMAAN | E12: PENGELUARAN | G12: KETERANGAN
C13: TANGGAL | D13: NOMINAL | E13: TANGGAL | F13: NOMINAL
A14: 1 | B14: UTJ SPK | C14: 46279 | D14: 39688200
A15: =A14+1 -> 2 | B15: KASBON VENDOR | E15: 46284 | F15: 10000000
A16: =A15+1 -> 3 | B16: KASBON VENDOR | E16: 46288 | F16: 5000000
A17: =A16+1 -> 4 | B17: TERMIN 1 | C17: 46289 | D17: 99220500
A18: =A17+1 -> 5 | B18: KASBON VENDOR | E18: 46290 | F18: 15000000
A19: 6 | B19: KASBON VENDOR | E19: 46291 | F19: 3500000
A20: 7 | B20: SALARY PENGAWAS | E20: 46266 | F20: 4000000 | G20: SALARY FERY
B24: OPERASIONAL | F24: =CIH!N63 -> 243900
A26: JUMLAH | D26: =SUM(D14:D25) -> 138908700 | F26: =SUM(F14:F25) -> 37743900
A27: KURANG BAYAR VENDOR | D27: =D9-D26 -> 257973300 | F27: =E5-SUM(F14:F23) -> 297500000

Sheet INTERIOR FRIZQI
A1: PROYEK INTERIOR BPK FRIZQI
B4: NO | C4: KET | D4: RAB | E4: RAP SUBKON | F4: FEE | G4: LABA | H4: % LABA
C5: SPK KAMAR DEPAN | D5: =36910820-15039000 -> 21871820 | E5: =25844000-10530000 -> 15314000 | G5: =D5-E5-F5 -> 6557820 | H5: =G5/D5*100 -> 29.982964
C6: SPK KAMAR BELAKANG | D6: 36545360 | E6: 25587000 | G6: =D6-E6-F6 -> 10958360 | H6: =G6/D6*100 -> 29.98564
H8: 0
C9: TOTAL | D9: =SUM(D5:D8) -> 58417180 | E9: =SUM(E5:E8) -> 40901000 | G9: =SUM(G5:G8) -> 17516180 | H9: =G9/D9*100 -> 29.984638
A12: NO. | B12: KET | C12: PENERIMAAN | E12: PENGELUARAN
C13: TANGGAL | D13: NOMINAL | E13: TANGGAL | F13: NOMINAL
A14: 1 | B14: UTJ SPK | C14: 46287 | D14: 50000000
A15: =A14+1 -> 2 | B15: KASBON VENDOR | E15: 46287 | F15: 10000000
A16: =A15+1 -> 3
A17: =A16+1 -> 4
A18: =A17+1 -> 5
A19: 6
B24: OPERASIONAL | F24: =CIH!N64 -> 208000
A26: JUMLAH | D26: =SUM(D14:D25) -> 50000000 | F26: =SUM(F14:F25) -> 10208000
A27: KURANG BAYAR VENDOR | D27: =D9-D26 -> 8417180 | F27: =E9-SUM(F14:F23) -> 30901000

Sheet LINTANG
A1: PROYEK RENOVASI IBU LINTANG
B4: NO | C4: KET | D4: RAB | E4: RAP SUBKON | F4: FEE | G4: LABA | H4: % LABA
B5: 1 | C5: SPK | D5: 23400000 | E5: =23000000*90% -> 20700000 | G5: =D5-E5-F5 -> 2700000 | H5: =G5/D5*100 -> 11.538462
H8: 0
C9: TOTAL | D9: =SUM(D5:D8) -> 23400000 | E9: =SUM(E5:E8) -> 20700000 | G9: =SUM(G5:G8) -> 2700000 | H9: =G9/D9*100 -> 11.538462
A12: NO. | B12: KET | C12: PENERIMAAN | E12: PENGELUARAN
C13: TANGGAL | D13: NOMINAL | E13: TANGGAL | F13: NOMINAL
A14: 1
A15: =A14+1 -> 2
A16: =A15+1 -> 3
A17: =A16+1 -> 4
A18: =A17+1 -> 5
A19: 6
B24: OPERASIONAL | F24: =CIH!N69 -> 140000
A26: JUMLAH | D26: =SUM(D14:D25) -> 0 | F26: =SUM(F14:F25) -> 140000
A27: KURANG BAYAR | D27: =D9-D26 -> 23400000

Sheet D. NANANG
A1: PROYEK DESAIN NANANG
B4: NO | C4: KET | D4: RAB | E4: RAP SUBKON | F4: FEE | G4: LABA | H4: % LABA
C5: SPK DESAIN | D5: 6000000 | E5: 3200000 | G5: =D5-E5-F5 -> 2800000 | H5: =G5/D5*100 -> 46.666667
C6: SPK DESAIN II | D6: =1750000*2 -> 3500000 | E6: 1700000 | G6: =D6-E6-F6 -> 1800000 | H6: =G6/D6*100 -> 51.428571
H8: 0
C9: TOTAL | D9: =SUM(D5:D8) -> 9500000 | E9: =SUM(E5:E8) -> 4900000 | G9: =SUM(G5:G8) -> 4600000 | H9: =G9/D9*100 -> 48.421053
A12: NO. | B12: KET | C12: PENERIMAAN | E12: PENGELUARAN SUBKON
C13: TANGGAL | D13: NOMINAL | E13: TANGGAL | F13: NOMINAL
A14: 1 | B14: DP | C14: 46171 | D14: 3000000
A15: =A14+1 -> 2 | B15: VENDOR | E15: 46214 | F15: 3200000
A16: =A15+1 -> 3 | B16: DP SPK II | C16: 46226 | D16: 1750000
A17: =A16+1 -> 4 | B17: VENDOR | E17: 46277 | F17: 1700000
A22: JUMLAH | D22: =SUM(D14:D21) -> 4750000 | F22: =SUM(F14:F21) -> 4900000
A23: KURANG BAYAR | D23: =D9-D22 -> 4750000 | F23: =E9-F22 -> 0

Sheet D. TENNY BEKASI
A1: PROYEK DESAIN INTERIOR KAMAR TENNY BEKASI
B4: NO | C4: KET | D4: RAB | E4: RAP SUBKON | F4: FEE | G4: LABA | H4: % LABA
C5: DESAIN | D5: 1200000 | G5: =D5-E5-F5 -> 1200000 | H5: =G5/D5*100 -> 100
G6: =D6-E6-F6 -> 0
H8: 0
C9: TOTAL | D9: =SUM(D5:D8) -> 1200000 | E9: =SUM(E5:E8) -> 0 | G9: =SUM(G5:G8) -> 1200000 | H9: =G9/D9*100 -> 100
A12: NO. | B12: KET | C12: PENERIMAAN | E12: PENGELUARAN SUBKON YUDI
C13: TANGGAL | D13: NOMINAL | E13: TANGGAL | F13: NOMINAL
A14: 1 | B14: DP | C14: 46210 | D14: 600000
A15: =A14+1 -> 2
A16: =A15+1 -> 3
A17: =A16+1 -> 4
A18: =A17+1 -> 5
B20: OPERASIONAL
A22: JUMLAH | D22: =SUM(D14:D21) -> 600000 | F22: =SUM(F14:F21) -> 0
A23: KURANG BAYAR | F23: =E9-F22 -> 0

Sheet D. HAMSJAH
A1: DESAIN BPK HAMSJAH
B4: NO | C4: KET | D4: RAB | E4: RAP SUBKON | F4: FEE | G4: LABA | H4: % LABA
C5: SPK | D5: =4200000*2 -> 8400000 | E5: =177.5*30000 -> 5325000 | G5: =D5-E5-F5 -> 3075000 | H5: =G5/D5*100 -> 36.607143
G6: =D6-E6-F6 -> 0
H8: 0
C9: TOTAL | D9: =SUM(D5:D8) -> 8400000 | E9: =SUM(E5:E8) -> 5325000 | G9: =SUM(G5:G8) -> 3075000 | H9: =G9/D9*100 -> 36.607143
A12: NO. | B12: KET | C12: PENERIMAAN | E12: PENGELUARAN
C13: TANGGAL | D13: NOMINAL | E13: TANGGAL | F13: NOMINAL
A14: 1 | B14: DP | C14: 46233 | D14: 4200000
A15: =A14+1 -> 2
A16: =A15+1 -> 3
A17: =A16+1 -> 4
A18: =A17+1 -> 5
B20: OPERASIONAL
A22: JUMLAH | D22: =SUM(D14:D21) -> 4200000 | F22: =SUM(F14:F21) -> 0
A23: KURANG BAYAR | D23: =D9-D22 -> 4200000

Sheet D. DEWI K24
A1: DESAIN IBU DEWI K24
B4: NO | C4: KET | D4: RAB | E4: RAP SUBKON | F4: FEE | G4: LABA | H4: % LABA
C5: SPK | D5: 6407500 | G5: =D5-E5-F5 -> 6407500 | H5: =G5/D5*100 -> 100
G6: =D6-E6-F6 -> 0
H8: 0
C9: TOTAL | D9: =SUM(D5:D8) -> 6407500 | E9: =SUM(E5:E8) -> 0 | G9: =SUM(G5:G8) -> 6407500 | H9: =G9/D9*100 -> 100
A12: NO. | B12: KET | C12: PENERIMAAN | E12: PENGELUARAN
C13: TANGGAL | D13: NOMINAL | E13: TANGGAL | F13: NOMINAL
A14: 1 | B14: DP | C14: 46241 | D14: =D5/2 -> 3203750
A15: =A14+1 -> 2 | B15: LUNAS | C15: 46263 | D15: 3203750
A16: =A15+1 -> 3
A17: =A16+1 -> 4
A18: =A17+1 -> 5
B20: OPERASIONAL | F20: =CIH!N56 -> 9500
A22: JUMLAH | D22: =SUM(D14:D21) -> 6407500 | F22: =SUM(F14:F21) -> 9500
A23: KURANG BAYAR | D23: =D9-D22 -> 0

Sheet D. LINDA
A1: PROYEK DESAIN IBU LINDA RUMAH 2 LANTAI
B4: NO | C4: KET | D4: RAB | E4: RAP SUBKON | F4: FEE | G4: LABA | H4: % LABA
C5: DESAIN | D5: 24000000 | G5: =D5-E5-F5 -> 24000000 | H5: =G5/D5*100 -> 100
G6: =D6-E6-F6 -> 0
H8: 0
C9: TOTAL | D9: =SUM(D5:D8) -> 24000000 | E9: =SUM(E5:E8) -> 0 | G9: =SUM(G5:G8) -> 24000000 | H9: =G9/D9*100 -> 100
A12: NO. | B12: KET | C12: PENERIMAAN | E12: PENGELUARAN SUBKON YUDI
C13: TANGGAL | D13: NOMINAL | E13: TANGGAL | F13: NOMINAL
A14: 1 | B14: DP | C14: 46270 | D14: 12000000
A15: =A14+1 -> 2
A16: =A15+1 -> 3
A17: =A16+1 -> 4
A18: =A17+1 -> 5
B20: OPERASIONAL | F20: =CIH!N60 -> 46000
A22: JUMLAH | D22: =SUM(D14:D21) -> 12000000 | F22: =SUM(F14:F21) -> 46000

Sheet D. SIGIT GEDANGAN
A1: PROYEK DESAIN INTERIOR BPK SIGIT
B4: NO | C4: KET | D4: RAB | E4: RAP SUBKON | F4: FEE | G4: LABA | H4: % LABA
C5: DESAIN | D5: 13000000 | G5: =D5-E5-F5 -> 13000000 | H5: =G5/D5*100 -> 100
G6: =D6-E6-F6 -> 0
H8: 0
C9: TOTAL | D9: =SUM(D5:D8) -> 13000000 | E9: =SUM(E5:E8) -> 0 | G9: =SUM(G5:G8) -> 13000000 | H9: =G9/D9*100 -> 100
A12: NO. | B12: KET | C12: PENERIMAAN | E12: PENGELUARAN SUBKON YUDI
C13: TANGGAL | D13: NOMINAL | E13: TANGGAL | F13: NOMINAL
A14: 1 | B14: DP | C14: 46270 | D14: 6500000
A15: =A14+1 -> 2
A16: =A15+1 -> 3
A17: =A16+1 -> 4
A18: =A17+1 -> 5
B20: OPERASIONAL | F20: =CIH!N59 -> 119000
A22: JUMLAH | D22: =SUM(D14:D21) -> 6500000 | F22: =SUM(F14:F21) -> 119000

Sheet D. DESY
A1: PROYEK DESAIN RUANG BELAKANG IBU DESY
B4: NO | C4: KET | D4: RAB | E4: RAP SUBKON | F4: FEE | G4: LABA | H4: % LABA
C5: DESAIN | D5: =920000*2 -> 1840000 | G5: =D5-E5-F5 -> 1840000 | H5: =G5/D5*100 -> 100
G6: =D6-E6-F6 -> 0
H8: 0
C9: TOTAL | D9: =SUM(D5:D8) -> 1840000 | E9: =SUM(E5:E8) -> 0 | G9: =SUM(G5:G8) -> 1840000 | H9: =G9/D9*100 -> 100
A12: NO. | B12: KET | C12: PENERIMAAN | E12: PENGELUARAN SUBKON YUDI
C13: TANGGAL | D13: NOMINAL | E13: TANGGAL | F13: NOMINAL
A14: 1 | B14: DP | C14: 46273 | D14: 920000
A15: =A14+1 -> 2
A16: =A15+1 -> 3
A17: =A16+1 -> 4
A18: =A17+1 -> 5
B20: OPERASINAL
A22: JUMLAH | D22: =SUM(D14:D21) -> 920000 | F22: =SUM(F14:F21) -> 0
A23: KURANG BAYAR | F23: =E9-F22 -> 0

Sheet D. DR MOLIS
A1: PROYEK DESAIN RUMAH 2 LANTAI DOKTER MOLIS
B4: NO | C4: KET | D4: RAB | E4: RAP SUBKON | F4: FEE | G4: LABA | H4: % LABA
C5: DESAIN | D5: =9000000*2 -> 18000000 | G5: =D5-E5-F5 -> 18000000 | H5: =G5/D5*100 -> 100
G6: =D6-E6-F6 -> 0
H8: 0
C9: TOTAL | D9: =SUM(D5:D8) -> 18000000 | E9: =SUM(E5:E8) -> 0 | G9: =SUM(G5:G8) -> 18000000 | H9: =G9/D9*100 -> 100
A12: NO. | B12: KET | C12: PENERIMAAN | E12: PENGELUARAN SUBKON YUDI
C13: TANGGAL | D13: NOMINAL | E13: TANGGAL | F13: NOMINAL
A14: 1 | B14: DP | C14: 46274 | D14: 9000000
A15: =A14+1 -> 2
A16: =A15+1 -> 3
A17: =A16+1 -> 4
A18: =A17+1 -> 5
B20: OPERASIONAL | F20: =CIH!N58 -> 279000
A22: JUMLAH | D22: =SUM(D14:D21) -> 9000000 | F22: =SUM(F14:F21) -> 279000
A23: KURANG BAYAR

Sheet D. ERLIS
A1: PROYEK DESAIN RUMAH 2 LANTAI IBU ERLIS
B4: NO | C4: KET | D4: RAB | E4: RAP SUBKON | F4: FEE | G4: LABA | H4: % LABA
C5: DESAIN | D5: =3570000*2 -> 7140000 | E5: =136.5*30000 -> 4095000 | G5: =D5-E5-F5 -> 3045000 | H5: =G5/D5*100 -> 42.647059
G6: =D6-E6-F6 -> 0
H8: 0
C9: TOTAL | D9: =SUM(D5:D8) -> 7140000 | E9: =SUM(E5:E8) -> 4095000 | G9: =SUM(G5:G8) -> 3045000 | H9: =G9/D9*100 -> 42.647059
A12: NO. | B12: KET | C12: PENERIMAAN | E12: PENGELUARAN SUBKON YUDI
C13: TANGGAL | D13: NOMINAL | E13: TANGGAL | F13: NOMINAL
A14: 1 | B14: DP | C14: 46274 | D14: 3570000
A15: =A14+1 -> 2
A16: =A15+1 -> 3
A17: =A16+1 -> 4
A18: =A17+1 -> 5
B20: OPERASIONAL | F20: =CIH!N61 -> 50000
A22: JUMLAH | D22: =SUM(D14:D21) -> 3570000 | F22: =SUM(F14:F21) -> 50000
A23: KURANG BAYAR

Sheet D. ARIEF JOMBANG
A1: PROYEK DESAIN ARIEF JOMBANG
B4: NO | C4: KET | D4: RAB | E4: RAP SUBKON | F4: FEE | G4: LABA | H4: % LABA
B5: 1 | C5: SPK DESAIN TIPE 36 | D5: =D15+D17 -> 1925000 | G5: =D5-E5-F5 -> 1925000 | H5: =G5/D5*100 -> 100
B6: 2 | C6: SPK DESAIN TIPE 46 | D6: =D16+D18 -> 3016000 | G6: =D6-E6-F6 -> 3016000 | H6: =G6/D6*100 -> 100
B7: 3 | C7: SPK BROSUR | D7: 900000 | E7: 0 | G7: =D7-E7-F7 -> 900000 | H7: =G7/D7*100 -> 100
B8: 4 | C8: SPK II TIPE 2 RUMAH | D8: 4860000 | G8: =D8-E8-F8 -> 4860000 | H8: =G8/D8*100 -> 100
H9: 0
C10: TOTAL | D10: =SUM(D5:D9) -> 10701000 | E10: =SUM(E5:E9) -> 0 | G10: =SUM(G5:G9) -> 10701000 | H10: =G10/D10*100 -> 100
A13: NO. | B13: KET | C13: PENERIMAAN | E13: PENGELUARAN SUBKON YUDI
C14: TANGGAL | D14: NOMINAL | E14: TANGGAL | F14: NOMINAL
A15: 1 | B15: DP 1 | C15: 46197 | D15: 960000
A16: =A15+1 -> 2 | B16: DP 2 | C16: 46197 | D16: 1140000
A17: =A16+1 -> 3 | B17: LUNAS 1 | C17: 46223 | D17: 965000
A18: =A17+1 -> 4 | B18: LUNAS 2 | C18: 46244 | D18: 1876000
A19: =A18+1 -> 5 | B19: LUNAS BROSUR | C19: 46255 | D19: 900000
A20: 6 | B20: DP SPK2 | C20: 46282 | D20: 2430000
B22: OPERASIONAL | F22: =CIH!N55 -> 700000
A24: JUMLAH | D24: =SUM(D15:D23) -> 8271000 | F24: =SUM(F15:F23) -> 700000
A25: KURANG BAYAR

Sheet D. JONI
A1: PROYEK DESAIN RUMAH 2 LANTAI BPK JONI
B4: NO | C4: KET | D4: RAB | E4: RAP SUBKON | F4: FEE | G4: LABA | H4: % LABA
C5: DESAIN | D5: 11520000 | G5: =D5-E5-F5 -> 11520000 | H5: =G5/D5*100 -> 100
G6: =D6-E6-F6 -> 0
H8: 0
C9: TOTAL | D9: =SUM(D5:D8) -> 11520000 | E9: =SUM(E5:E8) -> 0 | G9: =SUM(G5:G8) -> 11520000 | H9: =G9/D9*100 -> 100
A12: NO. | B12: KET | C12: PENERIMAAN | E12: PENGELUARAN SUBKON YUDI
C13: TANGGAL | D13: NOMINAL | E13: TANGGAL | F13: NOMINAL
A14: 1 | B14: DP | C14: 46286 | D14: 6000000
A15: =A14+1 -> 2
A16: =A15+1 -> 3
A17: =A16+1 -> 4
A18: =A17+1 -> 5
B20: OPERASIONAL
A22: JUMLAH | D22: =SUM(D14:D21) -> 6000000 | F22: =SUM(F14:F21) -> 0
A23: KURANG BAYAR | D23: =D9-D22 -> 5520000

Sheet D. NIKE
A1: PROYEK DESAIN RUMAH 2 LANTAI IBU NIKE
B4: NO | C4: KET | D4: RAB | E4: RAP SUBKON | F4: FEE | G4: LABA | H4: % LABA
C5: DESAIN | D5: 22500000 | G5: =D5-E5-F5 -> 22500000 | H5: =G5/D5*100 -> 100
G6: =D6-E6-F6 -> 0
H8: 0
C9: TOTAL | D9: =SUM(D5:D8) -> 22500000 | E9: =SUM(E5:E8) -> 0 | G9: =SUM(G5:G8) -> 22500000 | H9: =G9/D9*100 -> 100
A12: NO. | B12: KET | C12: PENERIMAAN | E12: PENGELUARAN SUBKON YUDI
C13: TANGGAL | D13: NOMINAL | E13: TANGGAL | F13: NOMINAL
A14: 1 | B14: DP | C14: 46286 | D14: 13500000
A15: =A14+1 -> 2
A16: =A15+1 -> 3
A17: =A16+1 -> 4
A18: =A17+1 -> 5
B20: OPERASIONAL | F20: =CIH!N65 -> 333000
A22: JUMLAH | D22: =SUM(D14:D21) -> 13500000 | F22: =SUM(F14:F21) -> 333000
A23: KURANG BAYAR | D23: =D9-D22 -> 9000000

Sheet D. ANGGA
A1: PROYEK DESAIN ME RUMAH 3 LANTAI BPK ANGGA
B4: NO | C4: KET | D4: RAB | E4: RAP SUBKON | F4: FEE | G4: LABA | H4: % LABA
C5: DESAIN | D5: =2172500*2 -> 4345000 | G5: =D5-E5-F5 -> 4345000 | H5: =G5/D5*100 -> 100
G6: =D6-E6-F6 -> 0
H8: 0
C9: TOTAL | D9: =SUM(D5:D8) -> 4345000 | E9: =SUM(E5:E8) -> 0 | G9: =SUM(G5:G8) -> 4345000 | H9: =G9/D9*100 -> 100
A12: NO. | B12: KET | C12: PENERIMAAN | E12: PENGELUARAN SUBKON YUDI
C13: TANGGAL | D13: NOMINAL | E13: TANGGAL | F13: NOMINAL
A14: 1 | B14: DP | C14: 46291 | D14: 2172500
A15: =A14+1 -> 2
A16: =A15+1 -> 3
A17: =A16+1 -> 4
A18: =A17+1 -> 5
B20: OPERASIONAL
A22: JUMLAH | D22: =SUM(D14:D21) -> 2172500 | F22: =SUM(F14:F21) -> 0
A23: KURANG BAYAR | D23: =D9-D22 -> 2172500

Sheet D. SAZA
A1: PROYEK DESAIN RUMAH 2 LANTAI IBU SAZA
B4: NO | C4: KET | D4: RAB | E4: RAP SUBKON | F4: FEE | G4: LABA | H4: % LABA
C5: DESAIN | D5: 3360000 | G5: =D5-E5-F5 -> 3360000 | H5: =G5/D5*100 -> 100
G6: =D6-E6-F6 -> 0
H8: 0
C9: TOTAL | D9: =SUM(D5:D8) -> 3360000 | E9: =SUM(E5:E8) -> 0 | G9: =SUM(G5:G8) -> 3360000 | H9: =G9/D9*100 -> 100
A12: NO. | B12: KET | C12: PENERIMAAN | E12: PENGELUARAN SUBKON YUDI
C13: TANGGAL | D13: NOMINAL | E13: TANGGAL | F13: NOMINAL
A14: 1 | B14: DP | C14: 46301 | D14: 1680000
A15: =A14+1 -> 2
A16: =A15+1 -> 3
A17: =A16+1 -> 4
A18: =A17+1 -> 5
B20: OPERASIONAL | F20: =CIH!N67 -> 252300
A22: JUMLAH | D22: =SUM(D14:D21) -> 1680000 | F22: =SUM(F14:F21) -> 252300
A23: KURANG BAYAR | D23: =D9-D22 -> 1680000

Sheet Sheet1

Sheet D. INGE
A1: PROYEK DESAIN RUMAH 2 LANTAI IBU INGE
B4: NO | C4: KET | D4: RAB | E4: RAP SUBKON | F4: FEE | G4: LABA | H4: % LABA
C5: DESAIN | D5: 6253750 | G5: =D5-E5-F5 -> 6253750 | H5: =G5/D5*100 -> 100
G6: =D6-E6-F6 -> 0
H8: 0
C9: TOTAL | D9: =SUM(D5:D8) -> 6253750 | E9: =SUM(E5:E8) -> 0 | G9: =SUM(G5:G8) -> 6253750 | H9: =G9/D9*100 -> 100
A12: NO. | B12: KET | C12: PENERIMAAN | E12: PENGELUARAN SUBKON YUDI
C13: TANGGAL | D13: NOMINAL | E13: TANGGAL | F13: NOMINAL
A14: 1 | B14: DP | C14: 46304 | D14: 1876125
A15: =A14+1 -> 2
A16: =A15+1 -> 3
A17: =A16+1 -> 4
A18: =A17+1 -> 5
B20: OPERASIONAL | F20: =CIH!N67 -> 252300
A22: JUMLAH | D22: =SUM(D14:D21) -> 1876125 | F22: =SUM(F14:F21) -> 252300
A23: KURANG BAYAR | D23: =D9-D22 -> 4377625
